setup.cfg
setup.py
Povidzion/__init__.py
Povidzion/liba.py
Povidzion.egg-info/PKG-INFO
Povidzion.egg-info/SOURCES.txt
Povidzion.egg-info/dependency_links.txt
Povidzion.egg-info/not-zip-safe
Povidzion.egg-info/top_level.txt