Metadata-Version: 1.0
Name: Povidzion
Version: 0.1
Summary: Why Not
Home-page: UNKNOWN
Author: UNKNOWN
Author-email: sanya14000@ukr.net
License: UNKNOWN
Platform: UNKNOWN
